{
  "erc_kind": "erc20",
  "chainId": 8453,
  "address": "0x7bfa7c4f149e7415b73bdedfe609237e29cbf34a",
  "symbol": "sparkUSDC",
  "decimals": 18,
  "name": "Spark USDC Vault",
  "source": "https://blue-api.morpho.org/graphql (MetaMorpho vault, listed) + etherscan/basescan verified",
  "token_kind": {
    "kind": "yield_receipt",
    "protocol": {
      "name": "metamorpho",
      "chain": "eip155:8453"
    },
    "underlying": {
      "key": {
        "standard": "erc20",
        "chain": "eip155:8453",
        "address": "0x833589fcd6edb6e08f4c7c32d4f71b54bda02913"
      }
    },
    "rebase_form": "index"
  }
}